{
  "product": "shortage-radar",
  "version": 2,
  "generated_at": "2026-05-22T07:57:11Z",
  "trail_legend": "月頻：本期與往回第3、6筆月資料（約各差一季）。週頻(EIA)：往回第0、13、26筆週資料。日頻：最近交易日與約91天、182天前的最近觀測；若來源僅提供短期滑動表（無法滿足182天），「約2季前」改為可取得之最舊觀測（畫面上標*）。",
  "categories": [
    "energy",
    "power",
    "semiconductor",
    "metals",
    "battery",
    "agriculture",
    "leading"
  ],
  "signals": [
    {
      "id": "energy_brent",
      "category": "energy",
      "category_zh": "能源",
      "display_zh": "Brent 原油（現貨）",
      "display_en": "Brent crude (spot)",
      "source": "fred",
      "score": 69.6,
      "latest": 116.73,
      "latest_date": "2026-05-18",
      "quarter_trail": [
        {
          "label": "本期",
          "date": "2026-05-18",
          "value": 116.73,
          "value_fmt": 116.73
        },
        {
          "label": "約1季前",
          "date": "2026-02-16",
          "value": 70.81,
          "value_fmt": 70.81
        },
        {
          "label": "約2季前",
          "date": "2025-11-17",
          "value": 63.16,
          "value_fmt": 63.16
        }
      ],
      "trail_mode": "daily",
      "notes": "FRED Brent 日頻；與 WTI 價差反映大西洋/中東运力與區域供需。",
      "detail": {
        "score": 69.6,
        "z_long": 2.175,
        "z_short": 2.112,
        "mom_30d_approx": 0.09,
        "latest": 116.73,
        "latest_date": "2026-05-18",
        "data_completeness": 100.0,
        "orientation": "high_is_tight",
        "trail_mode": "daily",
        "quarter_trail": [
          {
            "label": "本期",
            "date": "2026-05-18",
            "value": 116.73,
            "value_fmt": 116.73
          },
          {
            "label": "約1季前",
            "date": "2026-02-16",
            "value": 70.81,
            "value_fmt": 70.81
          },
          {
            "label": "約2季前",
            "date": "2025-11-17",
            "value": 63.16,
            "value_fmt": 63.16
          }
        ]
      }
    },
    {
      "id": "energy_eia_crude_inventory",
      "category": "energy",
      "category_zh": "能源",
      "display_zh": "美國原油庫存（EIA 週）",
      "display_en": "US crude oil ending stocks (EIA weekly, total)",
      "source": "eia_v2",
      "score": null,
      "latest": null,
      "latest_date": null,
      "quarter_trail": null,
      "trail_mode": null,
      "notes": "EIA API v2：`WCRSTUS1`（美國原油總庫存，千桶）；需免費 EIA_API_KEY。庫存下降 → 市場偏緊。",
      "detail": {
        "reason": "fetch_failed_or_empty",
        "hint": "若為 EIA：請在 repo 根 .env 設定 EIA_API_KEY（API v2，見 SETUP_KEYS.md）"
      }
    },
    {
      "id": "energy_henry_hub",
      "category": "energy",
      "category_zh": "能源",
      "display_zh": "Henry Hub 天然氣",
      "display_en": "Henry Hub natural gas",
      "source": "fred",
      "score": 53.6,
      "latest": 3.07,
      "latest_date": "2026-05-18",
      "quarter_trail": [
        {
          "label": "本期",
          "date": "2026-05-18",
          "value": 3.07,
          "value_fmt": 3.07
        },
        {
          "label": "約1季前",
          "date": "2026-02-13",
          "value": 3.24,
          "value_fmt": 3.24
        },
        {
          "label": "約2季前",
          "date": "2025-11-17",
          "value": 3.71,
          "value_fmt": 3.71
        }
      ],
      "trail_mode": "daily",
      "notes": "美國氣價基準；亞洲 JKM 常更高——美國便宜代表液化出口套利空間。",
      "detail": {
        "score": 53.6,
        "z_long": -0.197,
        "z_short": -0.201,
        "mom_30d_approx": 13.28,
        "latest": 3.07,
        "latest_date": "2026-05-18",
        "data_completeness": 100.0,
        "orientation": "high_is_tight",
        "trail_mode": "daily",
        "quarter_trail": [
          {
            "label": "本期",
            "date": "2026-05-18",
            "value": 3.07,
            "value_fmt": 3.07
          },
          {
            "label": "約1季前",
            "date": "2026-02-13",
            "value": 3.24,
            "value_fmt": 3.24
          },
          {
            "label": "約2季前",
            "date": "2025-11-17",
            "value": 3.71,
            "value_fmt": 3.71
          }
        ]
      }
    },
    {
      "id": "energy_ng_futures",
      "category": "energy",
      "category_zh": "能源",
      "display_zh": "美國天然氣期貨 (NG)",
      "display_en": "NYMEX natural gas front month",
      "source": "yahoo",
      "score": 52.9,
      "latest": 3.141,
      "latest_date": "2026-05-22",
      "quarter_trail": [
        {
          "label": "本期",
          "date": "2026-05-22",
          "value": 3.1410000324249268,
          "value_fmt": 3.141
        },
        {
          "label": "約1季前",
          "date": "2026-02-20",
          "value": 3.046999931335449,
          "value_fmt": 3.047
        },
        {
          "label": "約2季前",
          "date": "2025-11-21",
          "value": 4.579999923706055,
          "value_fmt": 4.58
        }
      ],
      "trail_mode": "daily",
      "notes": "Yahoo NG=F；對沖/投機較多，現貨用 Henry Hub 交叉驗證。",
      "detail": {
        "score": 52.9,
        "z_long": -0.388,
        "z_short": -0.37,
        "mom_30d_approx": 20.16,
        "latest": 3.141,
        "latest_date": "2026-05-22",
        "data_completeness": 100.0,
        "orientation": "high_is_tight",
        "trail_mode": "daily",
        "quarter_trail": [
          {
            "label": "本期",
            "date": "2026-05-22",
            "value": 3.1410000324249268,
            "value_fmt": 3.141
          },
          {
            "label": "約1季前",
            "date": "2026-02-20",
            "value": 3.046999931335449,
            "value_fmt": 3.047
          },
          {
            "label": "約2季前",
            "date": "2025-11-21",
            "value": 4.579999923706055,
            "value_fmt": 4.58
          }
        ]
      }
    },
    {
      "id": "energy_wti",
      "category": "energy",
      "category_zh": "能源",
      "display_zh": "WTI 原油（現貨）",
      "display_en": "WTI crude (spot proxy)",
      "source": "fred",
      "score": 81.2,
      "latest": 112.25,
      "latest_date": "2026-05-18",
      "quarter_trail": [
        {
          "label": "本期",
          "date": "2026-05-18",
          "value": 112.25,
          "value_fmt": 112.25
        },
        {
          "label": "約1季前",
          "date": "2026-02-13",
          "value": 63.05,
          "value_fmt": 63.05
        },
        {
          "label": "約2季前",
          "date": "2025-11-17",
          "value": 60.66,
          "value_fmt": 60.66
        }
      ],
      "trail_mode": "daily",
      "notes": "FRED WTI Cushing; 日頻。價格上行常反映供應緊張或地緣風險。",
      "detail": {
        "score": 81.2,
        "z_long": 2.71,
        "z_short": 2.637,
        "mom_30d_approx": 30.66,
        "latest": 112.25,
        "latest_date": "2026-05-18",
        "data_completeness": 100.0,
        "orientation": "high_is_tight",
        "trail_mode": "daily",
        "quarter_trail": [
          {
            "label": "本期",
            "date": "2026-05-18",
            "value": 112.25,
            "value_fmt": 112.25
          },
          {
            "label": "約1季前",
            "date": "2026-02-13",
            "value": 63.05,
            "value_fmt": 63.05
          },
          {
            "label": "約2季前",
            "date": "2025-11-17",
            "value": 60.66,
            "value_fmt": 60.66
          }
        ]
      }
    },
    {
      "id": "energy_wti_brent_spread",
      "category": "energy",
      "category_zh": "能源",
      "display_zh": "WTI–Brent 價差",
      "display_en": "WTI minus Brent spread",
      "source": "computed",
      "score": 45.8,
      "latest": -4.48,
      "latest_date": "2026-05-18",
      "quarter_trail": [
        {
          "label": "本期",
          "date": "2026-05-18",
          "value": -4.480000000000004,
          "value_fmt": -4.48
        },
        {
          "label": "約1季前",
          "date": "2026-02-13",
          "value": -6.909999999999997,
          "value_fmt": -6.91
        },
        {
          "label": "約2季前",
          "date": "2025-11-17",
          "value": -2.5,
          "value_fmt": -2.5
        }
      ],
      "trail_mode": "daily",
      "notes": "區域割裂指標；絕對值擴大時中游/物流瓶頸或品質/关税因素。",
      "detail": {
        "score": 45.8,
        "z_long": 0.272,
        "z_short": 0.308,
        "mom_30d_approx": -77.79,
        "latest": -4.48,
        "latest_date": "2026-05-18",
        "data_completeness": 100.0,
        "orientation": "high_is_tight",
        "trail_mode": "daily",
        "quarter_trail": [
          {
            "label": "本期",
            "date": "2026-05-18",
            "value": -4.480000000000004,
            "value_fmt": -4.48
          },
          {
            "label": "約1季前",
            "date": "2026-02-13",
            "value": -6.909999999999997,
            "value_fmt": -6.91
          },
          {
            "label": "約2季前",
            "date": "2025-11-17",
            "value": -2.5,
            "value_fmt": -2.5
          }
        ]
      }
    },
    {
      "id": "power_ceg",
      "category": "power",
      "category_zh": "AI 電力 (北美)",
      "display_zh": "Constellation Energy (CEG)",
      "display_en": "Constellation Energy",
      "source": "yahoo",
      "score": 37.6,
      "latest": 285.829987,
      "latest_date": "2026-05-21",
      "quarter_trail": [
        {
          "label": "本期",
          "date": "2026-05-21",
          "value": 285.8299865722656,
          "value_fmt": 285.83
        },
        {
          "label": "約1季前",
          "date": "2026-02-19",
          "value": 290.8178405761719,
          "value_fmt": 290.818
        },
        {
          "label": "約2季前",
          "date": "2025-11-20",
          "value": 344.78155517578125,
          "value_fmt": 344.782
        }
      ],
      "trail_mode": "daily",
      "notes": "美最大核電業者，MSFT 三哩島重啟 20 年 PPA；AI 24/7 baseload 直接受惠。",
      "detail": {
        "score": 37.6,
        "z_long": -1.132,
        "z_short": -1.154,
        "mom_30d_approx": -0.31,
        "latest": 285.829987,
        "latest_date": "2026-05-21",
        "data_completeness": 100.0,
        "orientation": "high_is_tight",
        "trail_mode": "daily",
        "quarter_trail": [
          {
            "label": "本期",
            "date": "2026-05-21",
            "value": 285.8299865722656,
            "value_fmt": 285.83
          },
          {
            "label": "約1季前",
            "date": "2026-02-19",
            "value": 290.8178405761719,
            "value_fmt": 290.818
          },
          {
            "label": "約2季前",
            "date": "2025-11-20",
            "value": 344.78155517578125,
            "value_fmt": 344.782
          }
        ]
      }
    },
    {
      "id": "power_gev",
      "category": "power",
      "category_zh": "AI 電力 (北美)",
      "display_zh": "GE Vernova (GEV)",
      "display_en": "GE Vernova",
      "source": "yahoo",
      "score": 68.6,
      "latest": 1043.819946,
      "latest_date": "2026-05-21",
      "quarter_trail": [
        {
          "label": "本期",
          "date": "2026-05-21",
          "value": 1043.8199462890625,
          "value_fmt": 1043.82
        },
        {
          "label": "約1季前",
          "date": "2026-02-19",
          "value": 834.1055908203125,
          "value_fmt": 834.106
        },
        {
          "label": "約2季前",
          "date": "2025-11-20",
          "value": 557.282470703125,
          "value_fmt": 557.282
        }
      ],
      "trail_mode": "daily",
      "notes": "氣渦輪製造龍頭，訂單能見度至 2028+；AI 數據中心新增容量的 capex 端代表。",
      "detail": {
        "score": 68.6,
        "z_long": 2.011,
        "z_short": 1.983,
        "mom_30d_approx": -7.43,
        "latest": 1043.819946,
        "latest_date": "2026-05-21",
        "data_completeness": 100.0,
        "orientation": "high_is_tight",
        "trail_mode": "daily",
        "quarter_trail": [
          {
            "label": "本期",
            "date": "2026-05-21",
            "value": 1043.8199462890625,
            "value_fmt": 1043.82
          },
          {
            "label": "約1季前",
            "date": "2026-02-19",
            "value": 834.1055908203125,
            "value_fmt": 834.106
          },
          {
            "label": "約2季前",
            "date": "2025-11-20",
            "value": 557.282470703125,
            "value_fmt": 557.282
          }
        ]
      }
    },
    {
      "id": "power_grid",
      "category": "power",
      "category_zh": "AI 電力 (北美)",
      "display_zh": "Smart Grid Infra ETF (GRID)",
      "display_en": "First Trust NASDAQ Smart Grid Infra ETF",
      "source": "yahoo",
      "score": 73.9,
      "latest": 190.979996,
      "latest_date": "2026-05-21",
      "quarter_trail": [
        {
          "label": "本期",
          "date": "2026-05-21",
          "value": 190.97999572753906,
          "value_fmt": 190.98
        },
        {
          "label": "約1季前",
          "date": "2026-02-19",
          "value": 174.5861053466797,
          "value_fmt": 174.586
        },
        {
          "label": "約2季前",
          "date": "2025-11-20",
          "value": 146.1047821044922,
          "value_fmt": 146.105
        }
      ],
      "trail_mode": "daily",
      "notes": "變壓器、開關、輸配電升級一籃子 ETF；北美電網 capex 需求的廣基代理。",
      "detail": {
        "score": 73.9,
        "z_long": 2.077,
        "z_short": 2.086,
        "mom_30d_approx": 3.8,
        "latest": 190.979996,
        "latest_date": "2026-05-21",
        "data_completeness": 100.0,
        "orientation": "high_is_tight",
        "trail_mode": "daily",
        "quarter_trail": [
          {
            "label": "本期",
            "date": "2026-05-21",
            "value": 190.97999572753906,
            "value_fmt": 190.98
          },
          {
            "label": "約1季前",
            "date": "2026-02-19",
            "value": 174.5861053466797,
            "value_fmt": 174.586
          },
          {
            "label": "約2季前",
            "date": "2025-11-20",
            "value": 146.1047821044922,
            "value_fmt": 146.105
          }
        ]
      }
    },
    {
      "id": "power_vst",
      "category": "power",
      "category_zh": "AI 電力 (北美)",
      "display_zh": "Vistra Corp (VST)",
      "display_en": "Vistra Corp",
      "source": "yahoo",
      "score": 33.1,
      "latest": 149.080002,
      "latest_date": "2026-05-21",
      "quarter_trail": [
        {
          "label": "本期",
          "date": "2026-05-21",
          "value": 149.0800018310547,
          "value_fmt": 149.08
        },
        {
          "label": "約1季前",
          "date": "2026-02-19",
          "value": 172.2650146484375,
          "value_fmt": 172.265
        },
        {
          "label": "約2季前",
          "date": "2025-11-20",
          "value": 173.3115997314453,
          "value_fmt": 173.312
        }
      ],
      "trail_mode": "daily",
      "notes": "核電 + 氣電混合 IPP；多家 hyperscaler 資料中心長約；AI 電力需求受惠。",
      "detail": {
        "score": 33.1,
        "z_long": -1.403,
        "z_short": -1.42,
        "mom_30d_approx": -4.31,
        "latest": 149.080002,
        "latest_date": "2026-05-21",
        "data_completeness": 100.0,
        "orientation": "high_is_tight",
        "trail_mode": "daily",
        "quarter_trail": [
          {
            "label": "本期",
            "date": "2026-05-21",
            "value": 149.0800018310547,
            "value_fmt": 149.08
          },
          {
            "label": "約1季前",
            "date": "2026-02-19",
            "value": 172.2650146484375,
            "value_fmt": 172.265
          },
          {
            "label": "約2季前",
            "date": "2025-11-20",
            "value": 173.3115997314453,
            "value_fmt": 173.312
          }
        ]
      }
    },
    {
      "id": "semi_soxx",
      "category": "semiconductor",
      "category_zh": "半導體",
      "display_zh": "費城半導體 ETF (SOXX)",
      "display_en": "SOXX ETF",
      "source": "yahoo",
      "score": 86.5,
      "latest": 524.710022,
      "latest_date": "2026-05-21",
      "quarter_trail": [
        {
          "label": "本期",
          "date": "2026-05-21",
          "value": 524.7100219726562,
          "value_fmt": 524.71
        },
        {
          "label": "約1季前",
          "date": "2026-02-19",
          "value": 355.62091064453125,
          "value_fmt": 355.621
        },
        {
          "label": "約2季前",
          "date": "2025-11-20",
          "value": 267.5429382324219,
          "value_fmt": 267.543
        }
      ],
      "trail_mode": "daily",
      "notes": "板塊風險情緒；上行未必等於缺貨，需跟產能/庫存新聞交叉驗證。",
      "detail": {
        "score": 86.5,
        "z_long": 2.94,
        "z_short": 2.94,
        "mom_30d_approx": 21.53,
        "latest": 524.710022,
        "latest_date": "2026-05-21",
        "data_completeness": 100.0,
        "orientation": "high_is_tight",
        "trail_mode": "daily",
        "quarter_trail": [
          {
            "label": "本期",
            "date": "2026-05-21",
            "value": 524.7100219726562,
            "value_fmt": 524.71
          },
          {
            "label": "約1季前",
            "date": "2026-02-19",
            "value": 355.62091064453125,
            "value_fmt": 355.621
          },
          {
            "label": "約2季前",
            "date": "2025-11-20",
            "value": 267.5429382324219,
            "value_fmt": 267.543
          }
        ]
      }
    },
    {
      "id": "semi_tsm_adr_tw_premium",
      "category": "semiconductor",
      "category_zh": "半導體",
      "display_zh": "台積電 ADR–台股溢價 (normalized %)",
      "display_en": "TSM ADR vs 2330.TW normalized spread",
      "source": "computed",
      "score": 43.4,
      "latest": -0.032082,
      "latest_date": "2026-05-21",
      "quarter_trail": [
        {
          "label": "本期",
          "date": "2026-05-21",
          "value": -0.03208209583349664,
          "value_fmt": -0.032082
        },
        {
          "label": "約1季前",
          "date": "2026-02-11",
          "value": -0.14476770280944518,
          "value_fmt": -0.144768
        },
        {
          "label": "約2季前",
          "date": "2025-11-20",
          "value": -7.396088480776064,
          "value_fmt": -7.396088
        }
      ],
      "trail_mode": "daily",
      "notes": "同公司兩市場價差 proxy（未含 ADR 換股比/匯率）；需四視角 triangulate。",
      "detail": {
        "score": 43.4,
        "z_long": 0.007,
        "z_short": 0.062,
        "mom_30d_approx": -99.25,
        "latest": -0.032082,
        "latest_date": "2026-05-21",
        "data_completeness": 100.0,
        "orientation": "high_is_tight",
        "trail_mode": "daily",
        "quarter_trail": [
          {
            "label": "本期",
            "date": "2026-05-21",
            "value": -0.03208209583349664,
            "value_fmt": -0.032082
          },
          {
            "label": "約1季前",
            "date": "2026-02-11",
            "value": -0.14476770280944518,
            "value_fmt": -0.144768
          },
          {
            "label": "約2季前",
            "date": "2025-11-20",
            "value": -7.396088480776064,
            "value_fmt": -7.396088
          }
        ]
      }
    },
    {
      "id": "metal_aluminum",
      "category": "metals",
      "category_zh": "工業金屬",
      "display_zh": "鋁 (IMF)",
      "display_en": "Aluminum",
      "source": "fred",
      "score": 78.6,
      "latest": 3372.952727,
      "latest_date": "2026-03-01",
      "quarter_trail": [
        {
          "label": "本期",
          "date": "2026-03-01",
          "value": 3372.952727272727,
          "value_fmt": 3372.953
        },
        {
          "label": "約1季前",
          "date": "2025-12-01",
          "value": 2875.897727272727,
          "value_fmt": 2875.898
        },
        {
          "label": "約2季前",
          "date": "2025-09-01",
          "value": 2654.479090909091,
          "value_fmt": 2654.479
        }
      ],
      "trail_mode": "monthly",
      "notes": "",
      "detail": {
        "score": 78.6,
        "z_long": 2.944,
        "z_short": 2.002,
        "mom_30d_approx": 17.28,
        "latest": 3372.952727,
        "latest_date": "2026-03-01",
        "data_completeness": 100.0,
        "orientation": "high_is_tight",
        "trail_mode": "monthly",
        "quarter_trail": [
          {
            "label": "本期",
            "date": "2026-03-01",
            "value": 3372.952727272727,
            "value_fmt": 3372.953
          },
          {
            "label": "約1季前",
            "date": "2025-12-01",
            "value": 2875.897727272727,
            "value_fmt": 2875.898
          },
          {
            "label": "約2季前",
            "date": "2025-09-01",
            "value": 2654.479090909091,
            "value_fmt": 2654.479
          }
        ]
      }
    },
    {
      "id": "metal_copper_fred",
      "category": "metals",
      "category_zh": "工業金屬",
      "display_zh": "銅 (IMF 月均值)",
      "display_en": "Copper (IMF via FRED)",
      "source": "fred",
      "score": 69.3,
      "latest": 12528.709545,
      "latest_date": "2026-03-01",
      "quarter_trail": [
        {
          "label": "本期",
          "date": "2026-03-01",
          "value": 12528.70954545455,
          "value_fmt": 12528.71
        },
        {
          "label": "約1季前",
          "date": "2025-12-01",
          "value": 11790.96409090909,
          "value_fmt": 11790.964
        },
        {
          "label": "約2季前",
          "date": "2025-09-01",
          "value": 9994.773181818182,
          "value_fmt": 9994.773
        }
      ],
      "trail_mode": "monthly",
      "notes": "全球工業溫度計；中國需求敏感。",
      "detail": {
        "score": 69.3,
        "z_long": 2.303,
        "z_short": 1.224,
        "mom_30d_approx": 6.26,
        "latest": 12528.709545,
        "latest_date": "2026-03-01",
        "data_completeness": 100.0,
        "orientation": "high_is_tight",
        "trail_mode": "monthly",
        "quarter_trail": [
          {
            "label": "本期",
            "date": "2026-03-01",
            "value": 12528.70954545455,
            "value_fmt": 12528.71
          },
          {
            "label": "約1季前",
            "date": "2025-12-01",
            "value": 11790.96409090909,
            "value_fmt": 11790.964
          },
          {
            "label": "約2季前",
            "date": "2025-09-01",
            "value": 9994.773181818182,
            "value_fmt": 9994.773
          }
        ]
      }
    },
    {
      "id": "metal_copper_futures",
      "category": "metals",
      "category_zh": "工業金屬",
      "display_zh": "COMEX 銅期貨",
      "display_en": "HG=F copper futures",
      "source": "yahoo",
      "score": 69.1,
      "latest": 6.3605,
      "latest_date": "2026-05-22",
      "quarter_trail": [
        {
          "label": "本期",
          "date": "2026-05-22",
          "value": 6.360499858856201,
          "value_fmt": 6.3605
        },
        {
          "label": "約1季前",
          "date": "2026-02-20",
          "value": 5.830999851226807,
          "value_fmt": 5.831
        },
        {
          "label": "約2季前",
          "date": "2025-11-21",
          "value": 5.008500099182129,
          "value_fmt": 5.0085
        }
      ],
      "trail_mode": "daily",
      "notes": "較 IMF 月頻更即時；可分鐘級情緒。",
      "detail": {
        "score": 69.1,
        "z_long": 1.847,
        "z_short": 1.799,
        "mom_30d_approx": 4.69,
        "latest": 6.3605,
        "latest_date": "2026-05-22",
        "data_completeness": 100.0,
        "orientation": "high_is_tight",
        "trail_mode": "daily",
        "quarter_trail": [
          {
            "label": "本期",
            "date": "2026-05-22",
            "value": 6.360499858856201,
            "value_fmt": 6.3605
          },
          {
            "label": "約1季前",
            "date": "2026-02-20",
            "value": 5.830999851226807,
            "value_fmt": 5.831
          },
          {
            "label": "約2季前",
            "date": "2025-11-21",
            "value": 5.008500099182129,
            "value_fmt": 5.0085
          }
        ]
      }
    },
    {
      "id": "metal_iron_ore",
      "category": "metals",
      "category_zh": "工業金屬",
      "display_zh": "鐵礦砂 (IMF)",
      "display_en": "Iron ore",
      "source": "fred",
      "score": 53.5,
      "latest": 107.577273,
      "latest_date": "2026-03-01",
      "quarter_trail": [
        {
          "label": "本期",
          "date": "2026-03-01",
          "value": 107.5772727272727,
          "value_fmt": 107.577
        },
        {
          "label": "約1季前",
          "date": "2025-12-01",
          "value": 107.5863636363636,
          "value_fmt": 107.586
        },
        {
          "label": "約2季前",
          "date": "2025-09-01",
          "value": 106.4090909090909,
          "value_fmt": 106.409
        }
      ],
      "trail_mode": "monthly",
      "notes": "",
      "detail": {
        "score": 53.5,
        "z_long": -0.237,
        "z_short": 1.011,
        "mom_30d_approx": -0.01,
        "latest": 107.577273,
        "latest_date": "2026-03-01",
        "data_completeness": 100.0,
        "orientation": "high_is_tight",
        "trail_mode": "monthly",
        "quarter_trail": [
          {
            "label": "本期",
            "date": "2026-03-01",
            "value": 107.5772727272727,
            "value_fmt": 107.577
          },
          {
            "label": "約1季前",
            "date": "2025-12-01",
            "value": 107.5863636363636,
            "value_fmt": 107.586
          },
          {
            "label": "約2季前",
            "date": "2025-09-01",
            "value": 106.4090909090909,
            "value_fmt": 106.409
          }
        ]
      }
    },
    {
      "id": "metal_lme_cu_inventory",
      "category": "metals",
      "category_zh": "工業金屬",
      "display_zh": "LME 銅倉庫庫存（Westmetall 表）",
      "display_en": "LME copper warehouse stocks (Westmetall mirror, tonnes)",
      "source": "westmetall_lme",
      "score": 41.1,
      "latest": 393100.0,
      "latest_date": "2026-05-21",
      "quarter_trail": [
        {
          "label": "本期",
          "date": "2026-05-21",
          "value": 393100.0,
          "value_fmt": 393100.0
        },
        {
          "label": "約1季前",
          "date": "2026-02-19",
          "value": 225575.0,
          "value_fmt": 225575.0
        },
        {
          "label": "約2季前",
          "date": "2026-01-02",
          "value": 145325.0,
          "value_fmt": 145325.0,
          "fallback": "oldest_in_series"
        }
      ],
      "trail_mode": "daily",
      "notes": "來源為 westmetall.com 匯總表（非 LME 官方 API）；庫存下降 → 偏緊。",
      "detail": {
        "score": 41.1,
        "z_long": 1.061,
        "z_short": 1.061,
        "mom_30d_approx": -1.37,
        "latest": 393100.0,
        "latest_date": "2026-05-21",
        "data_completeness": 100.0,
        "orientation": "low_is_tight",
        "trail_mode": "daily",
        "quarter_trail": [
          {
            "label": "本期",
            "date": "2026-05-21",
            "value": 393100.0,
            "value_fmt": 393100.0
          },
          {
            "label": "約1季前",
            "date": "2026-02-19",
            "value": 225575.0,
            "value_fmt": 225575.0
          },
          {
            "label": "約2季前",
            "date": "2026-01-02",
            "value": 145325.0,
            "value_fmt": 145325.0,
            "fallback": "oldest_in_series"
          }
        ]
      }
    },
    {
      "id": "metal_nickel",
      "category": "metals",
      "category_zh": "工業金屬",
      "display_zh": "鎳 (IMF)",
      "display_en": "Nickel",
      "source": "fred",
      "score": 62.0,
      "latest": 17076.292727,
      "latest_date": "2026-03-01",
      "quarter_trail": [
        {
          "label": "本期",
          "date": "2026-03-01",
          "value": 17076.29272727273,
          "value_fmt": 17076.293
        },
        {
          "label": "約1季前",
          "date": "2025-12-01",
          "value": 14879.03,
          "value_fmt": 14879.03
        },
        {
          "label": "約2季前",
          "date": "2025-09-01",
          "value": 15103.18363636364,
          "value_fmt": 15103.184
        }
      ],
      "trail_mode": "monthly",
      "notes": "",
      "detail": {
        "score": 62.0,
        "z_long": -0.012,
        "z_short": 1.393,
        "mom_30d_approx": 14.77,
        "latest": 17076.292727,
        "latest_date": "2026-03-01",
        "data_completeness": 100.0,
        "orientation": "high_is_tight",
        "trail_mode": "monthly",
        "quarter_trail": [
          {
            "label": "本期",
            "date": "2026-03-01",
            "value": 17076.29272727273,
            "value_fmt": 17076.293
          },
          {
            "label": "約1季前",
            "date": "2025-12-01",
            "value": 14879.03,
            "value_fmt": 14879.03
          },
          {
            "label": "約2季前",
            "date": "2025-09-01",
            "value": 15103.18363636364,
            "value_fmt": 15103.184
          }
        ]
      }
    },
    {
      "id": "metal_tin",
      "category": "metals",
      "category_zh": "工業金屬",
      "display_zh": "錫 (IMF)",
      "display_en": "Tin",
      "source": "fred",
      "score": 72.8,
      "latest": 47323.681818,
      "latest_date": "2026-03-01",
      "quarter_trail": [
        {
          "label": "本期",
          "date": "2026-03-01",
          "value": 47323.68181818182,
          "value_fmt": 47323.682
        },
        {
          "label": "約1季前",
          "date": "2025-12-01",
          "value": 41402.90909090909,
          "value_fmt": 41402.909
        },
        {
          "label": "約2季前",
          "date": "2025-09-01",
          "value": 34528.05772727273,
          "value_fmt": 34528.058
        }
      ],
      "trail_mode": "monthly",
      "notes": "",
      "detail": {
        "score": 72.8,
        "z_long": 2.41,
        "z_short": 1.37,
        "mom_30d_approx": 14.3,
        "latest": 47323.681818,
        "latest_date": "2026-03-01",
        "data_completeness": 100.0,
        "orientation": "high_is_tight",
        "trail_mode": "monthly",
        "quarter_trail": [
          {
            "label": "本期",
            "date": "2026-03-01",
            "value": 47323.68181818182,
            "value_fmt": 47323.682
          },
          {
            "label": "約1季前",
            "date": "2025-12-01",
            "value": 41402.90909090909,
            "value_fmt": 41402.909
          },
          {
            "label": "約2季前",
            "date": "2025-09-01",
            "value": 34528.05772727273,
            "value_fmt": 34528.058
          }
        ]
      }
    },
    {
      "id": "metal_zinc",
      "category": "metals",
      "category_zh": "工業金屬",
      "display_zh": "鋅 (IMF)",
      "display_en": "Zinc",
      "source": "fred",
      "score": 60.9,
      "latest": 3182.260909,
      "latest_date": "2026-03-01",
      "quarter_trail": [
        {
          "label": "本期",
          "date": "2026-03-01",
          "value": 3182.260909090909,
          "value_fmt": 3182.261
        },
        {
          "label": "約1季前",
          "date": "2025-12-01",
          "value": 3162.175,
          "value_fmt": 3162.175
        },
        {
          "label": "約2季前",
          "date": "2025-09-01",
          "value": 2936.735454545455,
          "value_fmt": 2936.735
        }
      ],
      "trail_mode": "monthly",
      "notes": "",
      "detail": {
        "score": 60.9,
        "z_long": 1.485,
        "z_short": 0.825,
        "mom_30d_approx": 0.64,
        "latest": 3182.260909,
        "latest_date": "2026-03-01",
        "data_completeness": 100.0,
        "orientation": "high_is_tight",
        "trail_mode": "monthly",
        "quarter_trail": [
          {
            "label": "本期",
            "date": "2026-03-01",
            "value": 3182.260909090909,
            "value_fmt": 3182.261
          },
          {
            "label": "約1季前",
            "date": "2025-12-01",
            "value": 3162.175,
            "value_fmt": 3162.175
          },
          {
            "label": "約2季前",
            "date": "2025-09-01",
            "value": 2936.735454545455,
            "value_fmt": 2936.735
          }
        ]
      }
    },
    {
      "id": "battery_alb_proxy",
      "category": "battery",
      "category_zh": "電池/轉型金屬",
      "display_zh": "雅寶 ALB（鋰/化工股價 proxy）",
      "display_en": "Albemarle (lithium equity proxy)",
      "source": "yahoo",
      "score": 53.5,
      "latest": 169.899994,
      "latest_date": "2026-05-21",
      "quarter_trail": [
        {
          "label": "本期",
          "date": "2026-05-21",
          "value": 169.89999389648438,
          "value_fmt": 169.9
        },
        {
          "label": "約1季前",
          "date": "2026-02-19",
          "value": 167.99383544921875,
          "value_fmt": 167.994
        },
        {
          "label": "約2季前",
          "date": "2025-11-20",
          "value": 115.78285217285156,
          "value_fmt": 115.783
        }
      ],
      "trail_mode": "daily",
      "notes": "非現貨鋰價；免費權宜。真實鋰價需 SMM 等（可後續爬蟲）。",
      "detail": {
        "score": 53.5,
        "z_long": 0.978,
        "z_short": 0.932,
        "mom_30d_approx": -12.52,
        "latest": 169.899994,
        "latest_date": "2026-05-21",
        "data_completeness": 100.0,
        "orientation": "high_is_tight",
        "trail_mode": "daily",
        "quarter_trail": [
          {
            "label": "本期",
            "date": "2026-05-21",
            "value": 169.89999389648438,
            "value_fmt": 169.9
          },
          {
            "label": "約1季前",
            "date": "2026-02-19",
            "value": 167.99383544921875,
            "value_fmt": 167.994
          },
          {
            "label": "約2季前",
            "date": "2025-11-20",
            "value": 115.78285217285156,
            "value_fmt": 115.783
          }
        ]
      }
    },
    {
      "id": "battery_cobalt",
      "category": "battery",
      "category_zh": "電池/轉型金屬",
      "display_zh": "全球電池金屬 ETF (BATT)",
      "display_en": "Global X Lithium & Battery Tech BATT",
      "source": "yahoo",
      "score": 61.6,
      "latest": 16.67,
      "latest_date": "2026-05-21",
      "quarter_trail": [
        {
          "label": "本期",
          "date": "2026-05-21",
          "value": 16.670000076293945,
          "value_fmt": 16.67
        },
        {
          "label": "約1季前",
          "date": "2026-02-19",
          "value": 15.5,
          "value_fmt": 15.5
        },
        {
          "label": "約2季前",
          "date": "2025-11-20",
          "value": 12.401337623596191,
          "value_fmt": 12.401338
        }
      ],
      "trail_mode": "daily",
      "notes": "FRED 無免費鈷現貨序列；用 BATT 作電池金屬一籃子 proxy。",
      "detail": {
        "score": 61.6,
        "z_long": 1.393,
        "z_short": 1.38,
        "mom_30d_approx": -2.0,
        "latest": 16.67,
        "latest_date": "2026-05-21",
        "data_completeness": 100.0,
        "orientation": "high_is_tight",
        "trail_mode": "daily",
        "quarter_trail": [
          {
            "label": "本期",
            "date": "2026-05-21",
            "value": 16.670000076293945,
            "value_fmt": 16.67
          },
          {
            "label": "約1季前",
            "date": "2026-02-19",
            "value": 15.5,
            "value_fmt": 15.5
          },
          {
            "label": "約2季前",
            "date": "2025-11-20",
            "value": 12.401337623596191,
            "value_fmt": 12.401338
          }
        ]
      }
    },
    {
      "id": "battery_sqm_proxy",
      "category": "battery",
      "category_zh": "電池/轉型金屬",
      "display_zh": "SQM（鋰 proxy）",
      "display_en": "SQM equity proxy",
      "source": "yahoo",
      "score": 55.9,
      "latest": 79.290001,
      "latest_date": "2026-05-21",
      "quarter_trail": [
        {
          "label": "本期",
          "date": "2026-05-21",
          "value": 79.29000091552734,
          "value_fmt": 79.290001
        },
        {
          "label": "約1季前",
          "date": "2026-02-19",
          "value": 71.28926849365234,
          "value_fmt": 71.289268
        },
        {
          "label": "約2季前",
          "date": "2025-11-20",
          "value": 59.839481353759766,
          "value_fmt": 59.839481
        }
      ],
      "trail_mode": "daily",
      "notes": "",
      "detail": {
        "score": 55.9,
        "z_long": 1.086,
        "z_short": 1.043,
        "mom_30d_approx": -7.77,
        "latest": 79.290001,
        "latest_date": "2026-05-21",
        "data_completeness": 100.0,
        "orientation": "high_is_tight",
        "trail_mode": "daily",
        "quarter_trail": [
          {
            "label": "本期",
            "date": "2026-05-21",
            "value": 79.29000091552734,
            "value_fmt": 79.290001
          },
          {
            "label": "約1季前",
            "date": "2026-02-19",
            "value": 71.28926849365234,
            "value_fmt": 71.289268
          },
          {
            "label": "約2季前",
            "date": "2025-11-20",
            "value": 59.839481353759766,
            "value_fmt": 59.839481
          }
        ]
      }
    },
    {
      "id": "agri_corn",
      "category": "agriculture",
      "category_zh": "農產品",
      "display_zh": "玉米期貨",
      "display_en": "Corn futures",
      "source": "yahoo",
      "score": 65.3,
      "latest": 464.5,
      "latest_date": "2026-05-22",
      "quarter_trail": [
        {
          "label": "本期",
          "date": "2026-05-22",
          "value": 464.5,
          "value_fmt": 464.5
        },
        {
          "label": "約1季前",
          "date": "2026-02-20",
          "value": 427.5,
          "value_fmt": 427.5
        },
        {
          "label": "約2季前",
          "date": "2025-11-21",
          "value": 425.5,
          "value_fmt": 425.5
        }
      ],
      "trail_mode": "daily",
      "notes": "",
      "detail": {
        "score": 65.3,
        "z_long": 1.551,
        "z_short": 1.578,
        "mom_30d_approx": 1.98,
        "latest": 464.5,
        "latest_date": "2026-05-22",
        "data_completeness": 100.0,
        "orientation": "high_is_tight",
        "trail_mode": "daily",
        "quarter_trail": [
          {
            "label": "本期",
            "date": "2026-05-22",
            "value": 464.5,
            "value_fmt": 464.5
          },
          {
            "label": "約1季前",
            "date": "2026-02-20",
            "value": 427.5,
            "value_fmt": 427.5
          },
          {
            "label": "約2季前",
            "date": "2025-11-21",
            "value": 425.5,
            "value_fmt": 425.5
          }
        ]
      }
    },
    {
      "id": "agri_food_index",
      "category": "agriculture",
      "category_zh": "農產品",
      "display_zh": "全球食品價格指數",
      "display_en": "Global food price index (IMF)",
      "source": "fred",
      "score": 66.7,
      "latest": 135.46351,
      "latest_date": "2026-03-01",
      "quarter_trail": [
        {
          "label": "本期",
          "date": "2026-03-01",
          "value": 135.4635099368799,
          "value_fmt": 135.464
        },
        {
          "label": "約1季前",
          "date": "2025-12-01",
          "value": 126.4738780948182,
          "value_fmt": 126.474
        },
        {
          "label": "約2季前",
          "date": "2025-09-01",
          "value": 126.6572419831769,
          "value_fmt": 126.657
        }
      ],
      "trail_mode": "monthly",
      "notes": "",
      "detail": {
        "score": 66.7,
        "z_long": 0.738,
        "z_short": 2.138,
        "mom_30d_approx": 7.11,
        "latest": 135.46351,
        "latest_date": "2026-03-01",
        "data_completeness": 100.0,
        "orientation": "high_is_tight",
        "trail_mode": "monthly",
        "quarter_trail": [
          {
            "label": "本期",
            "date": "2026-03-01",
            "value": 135.4635099368799,
            "value_fmt": 135.464
          },
          {
            "label": "約1季前",
            "date": "2025-12-01",
            "value": 126.4738780948182,
            "value_fmt": 126.474
          },
          {
            "label": "約2季前",
            "date": "2025-09-01",
            "value": 126.6572419831769,
            "value_fmt": 126.657
          }
        ]
      }
    },
    {
      "id": "agri_palm",
      "category": "agriculture",
      "category_zh": "農產品",
      "display_zh": "棕櫚油 (IMF)",
      "display_en": "Palm oil",
      "source": "fred",
      "score": 73.0,
      "latest": 1121.177897,
      "latest_date": "2026-03-01",
      "quarter_trail": [
        {
          "label": "本期",
          "date": "2026-03-01",
          "value": 1121.177897131898,
          "value_fmt": 1121.178
        },
        {
          "label": "約1季前",
          "date": "2025-12-01",
          "value": 981.2246703958918,
          "value_fmt": 981.225
        },
        {
          "label": "約2季前",
          "date": "2025-09-01",
          "value": 1034.900269774872,
          "value_fmt": 1034.9
        }
      ],
      "trail_mode": "monthly",
      "notes": "",
      "detail": {
        "score": 73.0,
        "z_long": 1.727,
        "z_short": 2.087,
        "mom_30d_approx": 14.26,
        "latest": 1121.177897,
        "latest_date": "2026-03-01",
        "data_completeness": 100.0,
        "orientation": "high_is_tight",
        "trail_mode": "monthly",
        "quarter_trail": [
          {
            "label": "本期",
            "date": "2026-03-01",
            "value": 1121.177897131898,
            "value_fmt": 1121.178
          },
          {
            "label": "約1季前",
            "date": "2025-12-01",
            "value": 981.2246703958918,
            "value_fmt": 981.225
          },
          {
            "label": "約2季前",
            "date": "2025-09-01",
            "value": 1034.900269774872,
            "value_fmt": 1034.9
          }
        ]
      }
    },
    {
      "id": "agri_soy",
      "category": "agriculture",
      "category_zh": "農產品",
      "display_zh": "黃豆期貨",
      "display_en": "Soybean futures",
      "source": "yahoo",
      "score": 67.5,
      "latest": 1199.0,
      "latest_date": "2026-05-22",
      "quarter_trail": [
        {
          "label": "本期",
          "date": "2026-05-22",
          "value": 1199.0,
          "value_fmt": 1199.0
        },
        {
          "label": "約1季前",
          "date": "2026-02-20",
          "value": 1137.5,
          "value_fmt": 1137.5
        },
        {
          "label": "約2季前",
          "date": "2025-11-21",
          "value": 1125.0,
          "value_fmt": 1125.0
        }
      ],
      "trail_mode": "daily",
      "notes": "",
      "detail": {
        "score": 67.5,
        "z_long": 1.749,
        "z_short": 1.694,
        "mom_30d_approx": 3.38,
        "latest": 1199.0,
        "latest_date": "2026-05-22",
        "data_completeness": 100.0,
        "orientation": "high_is_tight",
        "trail_mode": "daily",
        "quarter_trail": [
          {
            "label": "本期",
            "date": "2026-05-22",
            "value": 1199.0,
            "value_fmt": 1199.0
          },
          {
            "label": "約1季前",
            "date": "2026-02-20",
            "value": 1137.5,
            "value_fmt": 1137.5
          },
          {
            "label": "約2季前",
            "date": "2025-11-21",
            "value": 1125.0,
            "value_fmt": 1125.0
          }
        ]
      }
    },
    {
      "id": "lead_bdry",
      "category": "leading",
      "category_zh": "領先/總經",
      "display_zh": "BDI 乾散貨 ETF (BDRY)",
      "display_en": "BDRY ETF (dry bulk proxy)",
      "source": "yahoo",
      "score": 71.0,
      "latest": 12.5,
      "latest_date": "2026-05-21",
      "quarter_trail": [
        {
          "label": "本期",
          "date": "2026-05-21",
          "value": 12.5,
          "value_fmt": 12.5
        },
        {
          "label": "約1季前",
          "date": "2026-02-19",
          "value": 11.65999984741211,
          "value_fmt": 11.66
        },
        {
          "label": "約2季前",
          "date": "2025-11-20",
          "value": 8.920000076293945,
          "value_fmt": 8.92
        }
      ],
      "trail_mode": "daily",
      "notes": "波羅的海乾散貨的 ETF 近似；領先全球貿易量。",
      "detail": {
        "score": 71.0,
        "z_long": 1.794,
        "z_short": 1.823,
        "mom_30d_approx": 9.65,
        "latest": 12.5,
        "latest_date": "2026-05-21",
        "data_completeness": 100.0,
        "orientation": "high_is_tight",
        "trail_mode": "daily",
        "quarter_trail": [
          {
            "label": "本期",
            "date": "2026-05-21",
            "value": 12.5,
            "value_fmt": 12.5
          },
          {
            "label": "約1季前",
            "date": "2026-02-19",
            "value": 11.65999984741211,
            "value_fmt": 11.66
          },
          {
            "label": "約2季前",
            "date": "2025-11-20",
            "value": 8.920000076293945,
            "value_fmt": 8.92
          }
        ]
      }
    },
    {
      "id": "lead_durable_goods",
      "category": "leading",
      "category_zh": "領先/總經",
      "display_zh": "美國耐久財訂單",
      "display_en": "US durable goods orders",
      "source": "fred",
      "score": 56.7,
      "latest": 318909.0,
      "latest_date": "2026-03-01",
      "quarter_trail": [
        {
          "label": "本期",
          "date": "2026-03-01",
          "value": 318909.0,
          "value_fmt": 318909.0
        },
        {
          "label": "約1季前",
          "date": "2025-12-01",
          "value": 321342.0,
          "value_fmt": 321342.0
        },
        {
          "label": "約2季前",
          "date": "2025-09-01",
          "value": 314147.0,
          "value_fmt": 314147.0
        }
      ],
      "trail_mode": "monthly",
      "notes": "",
      "detail": {
        "score": 56.7,
        "z_long": 1.292,
        "z_short": 0.263,
        "mom_30d_approx": -0.76,
        "latest": 318909.0,
        "latest_date": "2026-03-01",
        "data_completeness": 100.0,
        "orientation": "high_is_tight",
        "trail_mode": "monthly",
        "quarter_trail": [
          {
            "label": "本期",
            "date": "2026-03-01",
            "value": 318909.0,
            "value_fmt": 318909.0
          },
          {
            "label": "約1季前",
            "date": "2025-12-01",
            "value": 321342.0,
            "value_fmt": 321342.0
          },
          {
            "label": "約2季前",
            "date": "2025-09-01",
            "value": 314147.0,
            "value_fmt": 314147.0
          }
        ]
      }
    },
    {
      "id": "lead_ism_pmi",
      "category": "leading",
      "category_zh": "領先/總經",
      "display_zh": "美國製造業工業生產 (IPMAN)",
      "display_en": "US Industrial Production: Manufacturing",
      "source": "fred",
      "score": 69.1,
      "latest": 98.6729,
      "latest_date": "2026-04-01",
      "quarter_trail": [
        {
          "label": "本期",
          "date": "2026-04-01",
          "value": 98.6729,
          "value_fmt": 98.6729
        },
        {
          "label": "約1季前",
          "date": "2026-01-01",
          "value": 97.6553,
          "value_fmt": 97.6553
        },
        {
          "label": "約2季前",
          "date": "2025-10-01",
          "value": 97.2128,
          "value_fmt": 97.2128
        }
      ],
      "trail_mode": "monthly",
      "notes": "FRED 上 ISM PMI 序列已不可取得；以 IPMAN 作製造業動能 proxy（非 PMI）。",
      "detail": {
        "score": 69.1,
        "z_long": 2.124,
        "z_short": 1.865,
        "mom_30d_approx": 1.04,
        "latest": 98.6729,
        "latest_date": "2026-04-01",
        "data_completeness": 100.0,
        "orientation": "high_is_tight",
        "trail_mode": "monthly",
        "quarter_trail": [
          {
            "label": "本期",
            "date": "2026-04-01",
            "value": 98.6729,
            "value_fmt": 98.6729
          },
          {
            "label": "約1季前",
            "date": "2026-01-01",
            "value": 97.6553,
            "value_fmt": 97.6553
          },
          {
            "label": "約2季前",
            "date": "2025-10-01",
            "value": 97.2128,
            "value_fmt": 97.2128
          }
        ]
      }
    },
    {
      "id": "lead_kr_exports",
      "category": "leading",
      "category_zh": "領先/總經",
      "display_zh": "韓國貨品出口（FRED）",
      "display_en": "Korea exports of goods (FRED IMF series)",
      "source": "fred",
      "score": 81.6,
      "latest": 84245570000.0,
      "latest_date": "2026-03-01",
      "quarter_trail": [
        {
          "label": "本期",
          "date": "2026-03-01",
          "value": 84245570000.0,
          "value_fmt": 84245570000.0
        },
        {
          "label": "約1季前",
          "date": "2025-12-01",
          "value": 65440510000.0,
          "value_fmt": 65440510000.0
        },
        {
          "label": "約2季前",
          "date": "2025-09-01",
          "value": 63211650000.0,
          "value_fmt": 63211650000.0
        }
      ],
      "trail_mode": "monthly",
      "notes": "IMT 貨品出口；免費 FRED。不需韓國 data.go.kr key。",
      "detail": {
        "score": 81.6,
        "z_long": 3.942,
        "z_short": 2.462,
        "mom_30d_approx": 28.74,
        "latest": 84245570000.0,
        "latest_date": "2026-03-01",
        "data_completeness": 100.0,
        "orientation": "high_is_tight",
        "trail_mode": "monthly",
        "quarter_trail": [
          {
            "label": "本期",
            "date": "2026-03-01",
            "value": 84245570000.0,
            "value_fmt": 84245570000.0
          },
          {
            "label": "約1季前",
            "date": "2025-12-01",
            "value": 65440510000.0,
            "value_fmt": 65440510000.0
          },
          {
            "label": "約2季前",
            "date": "2025-09-01",
            "value": 63211650000.0,
            "value_fmt": 63211650000.0
          }
        ]
      }
    },
    {
      "id": "lead_tw_export_orders",
      "category": "leading",
      "category_zh": "領先/總經",
      "display_zh": "台灣外銷訂單（經濟部 CSV）",
      "display_en": "Taiwan export orders (MOEA open data, USD millions)",
      "source": "tw_moea_csv",
      "score": 74.0,
      "latest": 87449.0,
      "latest_date": "2026-04-01",
      "quarter_trail": [
        {
          "label": "本期",
          "date": "2026-04-01",
          "value": 87449.0,
          "value_fmt": 87449.0
        },
        {
          "label": "約1季前",
          "date": "2026-01-01",
          "value": 76907.0,
          "value_fmt": 76907.0
        },
        {
          "label": "約2季前",
          "date": "2025-10-01",
          "value": 69434.0,
          "value_fmt": 69434.0
        }
      ],
      "trail_mode": "monthly",
      "notes": "https://service.moea.gov.tw/EE520/opendata/b.csv ；百萬美元；免 key。",
      "detail": {
        "score": 74.0,
        "z_long": 2.494,
        "z_short": 1.56,
        "mom_30d_approx": 13.71,
        "latest": 87449.0,
        "latest_date": "2026-04-01",
        "data_completeness": 100.0,
        "orientation": "high_is_tight",
        "trail_mode": "monthly",
        "quarter_trail": [
          {
            "label": "本期",
            "date": "2026-04-01",
            "value": 87449.0,
            "value_fmt": 87449.0
          },
          {
            "label": "約1季前",
            "date": "2026-01-01",
            "value": 76907.0,
            "value_fmt": 76907.0
          },
          {
            "label": "約2季前",
            "date": "2025-10-01",
            "value": 69434.0,
            "value_fmt": 69434.0
          }
        ]
      }
    },
    {
      "id": "lead_us_payems",
      "category": "leading",
      "category_zh": "領先/總經",
      "display_zh": "美國非農就業（水準，千人）",
      "display_en": "US Total Nonfarm Payrolls (PAYEMS, thousands)",
      "source": "fred",
      "score": 65.6,
      "latest": 158736.0,
      "latest_date": "2026-04-01",
      "quarter_trail": [
        {
          "label": "本期",
          "date": "2026-04-01",
          "value": 158736.0,
          "value_fmt": 158736.0
        },
        {
          "label": "約1季前",
          "date": "2026-01-01",
          "value": 158592.0,
          "value_fmt": 158592.0
        },
        {
          "label": "約2季前",
          "date": "2025-10-01",
          "value": 158408.0,
          "value_fmt": 158408.0
        }
      ],
      "trail_mode": "monthly",
      "notes": "FRED PAYEMS；每月第一個週五公布，本 cron 當天拿不到，隔日週六早報才出現新值。水準長期上升，z-score 偏高屬正常，請搭配月增減 instrument 判讀。",
      "detail": {
        "score": 65.6,
        "z_long": 1.119,
        "z_short": 2.288,
        "mom_30d_approx": 0.09,
        "latest": 158736.0,
        "latest_date": "2026-04-01",
        "data_completeness": 100.0,
        "orientation": "high_is_tight",
        "trail_mode": "monthly",
        "quarter_trail": [
          {
            "label": "本期",
            "date": "2026-04-01",
            "value": 158736.0,
            "value_fmt": 158736.0
          },
          {
            "label": "約1季前",
            "date": "2026-01-01",
            "value": 158592.0,
            "value_fmt": 158592.0
          },
          {
            "label": "約2季前",
            "date": "2025-10-01",
            "value": 158408.0,
            "value_fmt": 158408.0
          }
        ]
      }
    },
    {
      "id": "lead_us_payems_mom",
      "category": "leading",
      "category_zh": "領先/總經",
      "display_zh": "美國非農就業（月增減，千人）",
      "display_en": "US Nonfarm Payrolls MoM change (PAYEMS diff)",
      "source": "computed",
      "score": 48.2,
      "latest": 115.0,
      "latest_date": "2026-04-01",
      "quarter_trail": [
        {
          "label": "本期",
          "date": "2026-04-01",
          "value": 115.0,
          "value_fmt": 115.0
        },
        {
          "label": "約1季前",
          "date": "2026-01-01",
          "value": 160.0,
          "value_fmt": 160.0
        },
        {
          "label": "約2季前",
          "date": "2025-10-01",
          "value": -140.0,
          "value_fmt": -140.0
        }
      ],
      "trail_mode": "monthly",
      "notes": "PAYEMS 月環比差分（+175k 等同媒體常報數字）；新增偏強 → score 偏高，偏弱 → score 偏低。",
      "detail": {
        "score": 48.2,
        "z_long": 0.208,
        "z_short": 0.869,
        "mom_30d_approx": -28.12,
        "latest": 115.0,
        "latest_date": "2026-04-01",
        "data_completeness": 100.0,
        "orientation": "high_is_tight",
        "trail_mode": "monthly",
        "quarter_trail": [
          {
            "label": "本期",
            "date": "2026-04-01",
            "value": 115.0,
            "value_fmt": 115.0
          },
          {
            "label": "約1季前",
            "date": "2026-01-01",
            "value": 160.0,
            "value_fmt": 160.0
          },
          {
            "label": "約2季前",
            "date": "2025-10-01",
            "value": -140.0,
            "value_fmt": -140.0
          }
        ]
      }
    },
    {
      "id": "lead_us_unrate",
      "category": "leading",
      "category_zh": "領先/總經",
      "display_zh": "美國失業率（%）",
      "display_en": "US Unemployment Rate (UNRATE, %)",
      "source": "fred",
      "score": 46.6,
      "latest": 4.3,
      "latest_date": "2026-04-01",
      "quarter_trail": [
        {
          "label": "本期",
          "date": "2026-04-01",
          "value": 4.3,
          "value_fmt": 4.3
        },
        {
          "label": "約1季前",
          "date": "2026-01-01",
          "value": 4.3,
          "value_fmt": 4.3
        },
        {
          "label": "約2季前",
          "date": "2025-09-01",
          "value": 4.4,
          "value_fmt": 4.4
        }
      ],
      "trail_mode": "monthly",
      "notes": "FRED UNRATE；低失業率 = 勞動市場緊俏 → orientation=low_is_tight。與 NFP 同天公布。",
      "detail": {
        "score": 46.6,
        "z_long": 0.909,
        "z_short": -0.162,
        "mom_30d_approx": 0.0,
        "latest": 4.3,
        "latest_date": "2026-04-01",
        "data_completeness": 100.0,
        "orientation": "low_is_tight",
        "trail_mode": "monthly",
        "quarter_trail": [
          {
            "label": "本期",
            "date": "2026-04-01",
            "value": 4.3,
            "value_fmt": 4.3
          },
          {
            "label": "約1季前",
            "date": "2026-01-01",
            "value": 4.3,
            "value_fmt": 4.3
          },
          {
            "label": "約2季前",
            "date": "2025-09-01",
            "value": 4.4,
            "value_fmt": 4.4
          }
        ]
      }
    }
  ]
}